aiida_s3/__init__.py
aiida_s3/py.typed
aiida_s3/cli/__init__.py
aiida_s3/cli/cmd_profile.py
aiida_s3/repository/__init__.py
aiida_s3/repository/aws_s3.py
aiida_s3/repository/azure_blob.py
aiida_s3/repository/s3.py
aiida_s3/storage/__init__.py
aiida_s3/storage/psql_aws_s3.py
aiida_s3/storage/psql_azure_blob.py
aiida_s3/storage/psql_dos.py
aiida_s3/storage/psql_s3.py
aiida_s3-0.2.0.dist-info/entry_points.txt
aiida_s3-0.2.0.dist-info/LICENSE.txt
aiida_s3-0.2.0.dist-info/WHEEL
aiida_s3-0.2.0.dist-info/METADATA
aiida_s3-0.2.0.dist-info/RECORD
