Metadata-Version: 2.1
Name: aiida-s3
Version: 0.2.0
Summary: AiiDA plugin that provides a storage backend using an S3 object store as the file repository.
Keywords: aiida,workflows,s3
Author-email: "Sebastiaan P. Huber" <mail@sphuber.net>
Requires-Python: >=3.8
Classifier: Development Status :: 4 - Beta
Classifier: Framework :: AiiDA
Classifier: License :: OSI Approved :: MIT License
Classifier: Operating System :: POSIX :: Linux
Classifier: Operating System :: MacOS :: MacOS X
Classifier: Programming Language :: Python
Classifier: Programming Language :: Python :: 3.8
Classifier: Programming Language :: Python :: 3.9
Classifier: Programming Language :: Python :: 3.10
Classifier: Programming Language :: Python :: 3.11
Classifier: Topic :: Scientific/Engineering
Requires-Dist: aiida-core~=2.2
Requires-Dist: azure-storage-blob
Requires-Dist: boto3
Requires-Dist: mypy==0.981 ; extra == "pre-commit"
Requires-Dist: pre-commit~=2.17 ; extra == "pre-commit"
Requires-Dist: pylint~=2.12.2 ; extra == "pre-commit"
Requires-Dist: pylint-aiida~=0.1.1 ; extra == "pre-commit"
Requires-Dist: types-pyyaml ; extra == "pre-commit"
Requires-Dist: moto[s3] ; extra == "tests"
Requires-Dist: pgtest~=1.3,>=1.3.1 ; extra == "tests"
Requires-Dist: pytest~=7.2 ; extra == "tests"
Project-URL: changelog, https://github.com/sphuber/aiida-s3/blob/master/CHANGELOG.md
Project-URL: documentation, https://github.com/sphuber/aiida-s3/blob/master/README.md
Project-URL: source, https://github.com/sphuber/aiida-s3
Project-URL: tracker, https://github.com/sphuber/aiida-s3/issues
Provides-Extra: pre-commit
Provides-Extra: tests
